{
    "version": "3.0.36",
    "architecture": {
        "64bit": {
            "url": "https://github.com/budimanjojo/talhelper/releases/download/v3.0.36/talhelper_windows_amd64.tar.gz",
            "bin": [
                "talhelper.exe"
            ],
            "hash": "4cd3e3604b9dbb95b736df4900a4c9df3c3741468e05098cf38c3aceb98a2ff2"
        }
    },
    "homepage": "https://github.com/budimanjojo/talhelper",
    "license": "BSD-3",
    "description": "A tool to help creating Talos kubernetes cluster",
    "depends": [
        "sops"
    ]
}
